setup.py
seltest/__init__.py
seltest/cli.py
seltest/helpers.py
seltest/proxy.py
seltest/seltest.py
seltest.egg-info/PKG-INFO
seltest.egg-info/SOURCES.txt
seltest.egg-info/dependency_links.txt
seltest.egg-info/entry_points.txt
seltest.egg-info/requires.txt
seltest.egg-info/top_level.txt
test/test.py