Metadata-Version: 1.1
Name: seltest
Version: 0.2.0
Summary: A perceptual difference testing framework for writing the easiest, most comprehensive tests you can run.
Home-page: https://github.com/ihodes/seltest/
Author: Isaac Hodes
Author-email: isaachodes@gmail.com
License: UNKNOWN
Keywords: pdiff,testing,perceptual
Platform: UNKNOWN
Classifier: Development Status :: 4 - Beta
Classifier: Intended Audience :: Developers
Classifier: License :: OSI Approved :: Apache Software License
Classifier: Topic :: Utilities
Classifier: Topic :: Software Development :: Testing
